{
  "results": [
    {
      "n_components": 10,
      "variance_sum": 0.3307846188545227,
      "test_auc": 0.9993388186893917,
      "brier": 0.007762142448217258,
      "feature_dim": 17,
      "calibrated": true,
      "sentiment_dim": 7
    },
    {
      "n_components": 20,
      "variance_sum": 0.4519270956516266,
      "test_auc": 0.9997061416397296,
      "brier": 0.006078154771747294,
      "feature_dim": 27,
      "calibrated": true,
      "sentiment_dim": 7
    },
    {
      "n_components": 30,
      "variance_sum": 0.530308187007904,
      "test_auc": 0.9999632677049662,
      "brier": 0.004647658977709167,
      "feature_dim": 37,
      "calibrated": true,
      "sentiment_dim": 7
    },
    {
      "n_components": 40,
      "variance_sum": 0.5882652997970581,
      "test_auc": 0.9998898031148986,
      "brier": 0.004433920698078514,
      "feature_dim": 47,
      "calibrated": true,
      "sentiment_dim": 7
    },
    {
      "n_components": 50,
      "variance_sum": 0.63303142786026,
      "test_auc": 0.9998530708198649,
      "brier": 0.004136742934915081,
      "feature_dim": 57,
      "calibrated": true,
      "sentiment_dim": 7
    }
  ],
  "best": {
    "n_components": 10,
    "variance_sum": 0.3307846188545227,
    "test_auc": 0.9993388186893917,
    "brier": 0.007762142448217258,
    "feature_dim": 17,
    "calibrated": true,
    "sentiment_dim": 7
  },
  "tolerance": 0.001
}